lignum/__init__.py
lignum-0.0.3.dist-info/METADATA
lignum-0.0.3.dist-info/WHEEL
lignum-0.0.3.dist-info/RECORD
