Metadata-Version: 2.3
Name: lignum
Version: 0.0.3
Summary: A teensy structured JSON logger for python.
Project-URL: Homepage, https://github.com/rsigrest/lignum
Project-URL: Repository, https://github.com/rsigrest/lignum.git
Author-email: Rob Sigrest <rob.sigrest@gmail.com>
Provides-Extra: test
Requires-Dist: flake8==7.1.1; extra == 'test'
Requires-Dist: pytest==8.3.2; extra == 'test'
